Linq-0.3.1.dist-info/DESCRIPTION.rst
Linq-0.3.1.dist-info/METADATA
Linq-0.3.1.dist-info/RECORD
Linq-0.3.1.dist-info/WHEEL
Linq-0.3.1.dist-info/metadata.json
Linq-0.3.1.dist-info/top_level.txt
linq/__init__.py
linq/core/__init__.py
linq/core/collections.py
linq/core/flow.py
linq/core/utils.py
linq/standard/__init__.py
linq/standard/dict.py
linq/standard/general.py
linq/standard/generator.py
linq/standard/list.py
linq/standard/set.py
