Metadata-Version: 2.0
Name: Linq
Version: 0.3.1
Summary: Language Integrated Query for Python
Home-page: https://github.com/thautwarm/Linq.py/
Author: thautwarm
Author-email: twshere@outlook.com
License: MIT
Keywords: Linq
Platform: UNKNOWN
Classifier: Programming Language :: Python :: 3.4
Classifier: Programming Language :: Python :: 3.5
Classifier: Programming Language :: Python :: 3.6
Classifier: Programming Language :: Python :: 3.7
Classifier: Programming Language :: Python :: Implementation :: CPython
